.DS_Store
CHANGELOG.txt
CNN_Model.pkl
LICENCE.txt
MANIFEST.in
My_Smiley_Helper.py
My_Smiley_Model.py
README.txt
Test_Image.png
UI.py
__init__.py
packages.txt
requirements.txt
setup.py
__pycache__/Helper.cpython-37.pyc
__pycache__/Model.cpython-37.pyc
__pycache__/My_Smiley_Helper.cpython-37.pyc
__pycache__/My_Smiley_Model.cpython-37.pyc
dist/paul_smiley_prediction-0.0.1.tar.gz
paul_smiley_prediction.egg-info/PKG-INFO
paul_smiley_prediction.egg-info/SOURCES.txt
paul_smiley_prediction.egg-info/dependency_links.txt
paul_smiley_prediction.egg-info/requires.txt
paul_smiley_prediction.egg-info/top_level.txt