Metadata-Version: 1.1
Name: paul-smiley-prediction
Version: 0.0.1
Summary: Smiley face predictior
Home-page: UNKNOWN
Author: Paul Fentress
Author-email: fentresspaul@berkeley.edu
License: MIT
Keywords: Smiley Face
Platform: UNKNOWN
Classifier: Development Status :: 1 - Planning
Classifier: Intended Audience :: Education
Classifier: Operating System :: MacOS :: MacOS X
Classifier: License :: OSI Approved :: MIT License
Classifier: Programming Language :: Python :: 3
